[
  {
    "job_id": "26035_20800_REF11862C",
    "title": "Care Assistant",
    "company": "The Human Support Group Limited - Agency - Permanent",
    "location": "Doncaster",
    "region": "South Yorkshire",
    "country": "UK",
    "category": "Support Worker – Wide",
    "employment_type": "Permanent",
    "salary_min": "",
    "salary_max": "",
    "salary_text": "£13.00 per hour",
    "posted_date": "",
    "description": "Company Description\n\nCompany Description\n\nAt CCH Group, we're more than a care provider - we're a passionate community dedicated to driving the sector to new heights with a history of doing so. Founded in 2009, we've grown into the nation's largest care company, with over 260 locations and 14,000 care professionals delivering 1.5 million hours of care each month across the UK.\n\nJob Description\n\nAre you a compassionate and dedicated Care Assistant seeking a fulfilling role? CCH are looking for individuals like you to join our team\n\nRole summary\n\nPay Rate - £13.00 per hour\nLocation - Doncaster\nHours - Evenings 3-10pm and weekends flexible\n\nApplicants must have the Right to Work in the UK. We are unable to offer sponsorship\n\nAbout the position\n\nCCH is in search of a caring and empathetic Care Assistant to provide dedicated support to the local people of Wheatley, ensuring their needs are met with kindness and professionalism.\n\nAs an integral member of CCH, you'll play a vital role in enhancing the well-being and quality of life of each individual under your care.\n\nNo experience? No problem. Whether you're starting your career or bringing past care experience, what matters most is your heart.\n\nYour responsibilities will include\n- Companionship - being a friendly face & preventing loneliness\n- Personal Care - all aspects of personal hygiene\n- Medication - collecting prescriptions & providing reminders\n- Mealtimes - preparing tasty meals\n- Housekeeping - keeping their home just the way they like it\n- Mobility - help with getting around\n\nThe Successful Assistant will ensure this is done with the highest level of understanding and dignity for our clients.\n\nIf you're ready to embark on a rewarding journey where every interaction counts, join us in creating a warm and supportive environment with our clients.\n\nQualifications\n\nWhat you'll bring to the team\n- Proficient in effective communication across all levels\n- Demonstrates a sincere interest in working with our specific client group\n- Successfully passed DBS screening\n- Patience, compassion & a positive attitude at all times\n- Demonstrate eagerness to engage in vocational training programs, continually enhancing skills and knowledge\n- Display initiative and autonomy\n\nAdditional Information\n\nWho We Are:\n\nAt CCH Group, our vision is to become the best place to work in care. Our mission is to expand our reach so that those in need of care are never forgotten or alone. We achieve this by nurturing our people, elevating their roles in society, and transforming lives together.\n\nOur Values:\n- COMMUNITY: We are stronger together. One team building a culture where our customers and people thrive.\n- COURAGE: We boldly shape a better future, tackling challenges head-on.\n- HEART: We are passionate and dedicated-we love what we do because what we do matters.\n\nWhat's in it for you\n- Enhanced occupational maternity and adoption pay\n- Enhanced occupational paternity pay entitlement\n- Death in Service Payment\n- Pension scheme\n- Benefits and Well-being Platform\n- 28 days annual leave (pro rata)\n- Cycle to work scheme\n- Refer a friend scheme - earn £300 per referral!\n- Blue Light Card eligibility - exclusive staff discounts at big brands for you\n- Flexible hours, part and full time available\n- Local work and paid mileage\n- Paid training\n- Self-development - progression opportunities\n- Access to our in-house app\n- Work for the largest care company in the UK!\n- No experience necessary\n- Book an interview at a time and date to suit you!\n\nReady to Take the Next Step?\n\nApply today and become part of a team that's transforming lives, one person at a time.\n\nCCH Group is an Equal Opportunities Employer and a proud member of the Home Care Association, adhering to their Code of Practice.",
    "apply_url": "https://www.jobg8.com/Traffic.aspx?wTAUM266l6dNU5F6T43kWh7JN5MaCEGDh",
    "source": "JobG8"
  },
  {
    "job_id": "26035_20800_REF11757I",
    "title": "Care Assistant",
    "company": "Comfort Call Limited - Agency - Permanent",
    "location": "Rotherham",
    "region": "South Yorkshire",
    "country": "UK",
    "category": "Support Worker – Wide",
    "employment_type": "Permanent",
    "salary_min": "",
    "salary_max": "",
    "salary_text": "£13.50 per hour",
    "posted_date": "",
    "description": "Company Description\n\nCompany Description\n\nAt CCH Group, we're more than a care provider - we're a passionate community dedicated to driving the sector to new heights with a history of doing so. Founded in 2009, we've grown into the nation's largest care company, with over 260 locations and 14,000 care professionals delivering 1.5 million hours of care each month across the UK.\n\nJob Description\n\nAre you a compassionate and dedicated Care Assistant seeking a fulfilling role? CCH are looking for individuals like you to join our team\n\nRole summary\n\nPay Rate - £13.50 per hour plus mileage\nLocation - Herringthorpe and surrounding areas\nHours - Flexible\n\nAbout the position\n\nCCH is in search of caring and empathetic Care Assistants to provide dedicated support to the local people of Rotherham, ensuring their needs are met with kindness and professionalism.\n\nAs an integral member of CCH, you'll play a vital role in enhancing the well-being and quality of life of each individual under your care.\n\nYour responsibilities will include\n- Companionship - being a friendly face & preventing loneliness\n- Personal Care - all aspects of personal hygiene\n- Medication - collecting prescriptions & providing reminders\n- Mealtimes - preparing tasty meals\n- Housekeeping - keeping their home just the way they like it\n- Mobility - help with getting around\n\nThe Successful Care Assistant will ensure this is done with the highest level of understanding and dignity for our clients.\n\nIf you're ready to embark on a rewarding journey where every interaction counts, join us in creating a warm and supportive environment with our clients.\n\nQualifications\n\nWhat you'll bring to the team\n- Proficient in effective communication across all levels\n- Demonstrates a sincere interest in working with our specific client group\n- Successfully passed DBS screening\n- Patience, compassion & a positive attitude at all times\n- Demonstrate eagerness to engage in vocational training programs, continually enhancing skills and knowledge\n- Display initiative and autonomy\n\nAdditional Information\n\nWho We Are:\n\nAt CCH Group, our vision is to become the best place to work in care. Our mission is to expand our reach so that those in need of care are never forgotten or alone. We achieve this by nurturing our people, elevating their roles in society, and transforming lives together.\n\nOur Values:\n- COMMUNITY: We are stronger together. One team building a culture where our customers and people thrive.\n- COURAGE: We boldly shape a better future, tackling challenges head-on.\n- HEART: We are passionate and dedicated-we love what we do because what we do matters.\n\nWhat's in it for you\n- Enhanced occupational maternity and adoption pay\n- Enhanced occupational paternity pay entitlement\n- Death in Service Payment\n- Pension scheme\n- Benefits and Well-being Platform\n- 28 days annual leave (pro rata)\n- Cycle to work scheme\n- Refer a friend scheme - earn £300 per referral!\n- Blue Light Card eligibility - exclusive staff discounts at big brands for you\n- Flexible hours, part and full time available\n- Local work and paid mileage\n- Paid training\n- Self-development - progression opportunities\n- Access to our in-house app\n- Work for the largest care company in the UK!\n- No experience necessary\n- Book an interview at a time and date to suit you!\n\nReady to Take the Next Step?\n\nApply today and become part of a team that's transforming lives, one person at a time.\n\nCCH Group is an Equal Opportunities Employer and a proud member of the Home Care Association, adhering to their Code of Practice.",
    "apply_url": "https://www.jobg8.com/Traffic.aspx?ju9emE%2fz0VIigOnfU2gUc7LRNKDvAnqLw",
    "source": "JobG8"
  },
  {
    "job_id": "52e8a656-b195-4919-b776-6f15f4f25694",
    "title": "Waking Night Support Worker",
    "company": "Creative Support Ltd - Company - Permanent",
    "location": "Barnsley",
    "region": "South Yorkshire",
    "country": "UK",
    "category": "Support Worker – Wide",
    "employment_type": "Permanent",
    "salary_min": "13.71",
    "salary_max": "13.71",
    "salary_text": "£13.71 per hour",
    "posted_date": "",
    "description": "We are seeking warm, caring individuals to provide personalised care and support throughout the night in our extra care services located in Royston, Barnsley. These services enable older people to maintain their wellbeing and enjoy an active and independent lifestyle. We can offer you 1 night per week with the opportunity to work additional hours on a flexible basis.\n\nWe are looking for compassionate, respectful and dependable individuals who are passionate about supporting others. The ideal candidate will demonstrate professionalism, accountability, and a strong commitment to safeguarding and person-centered care. Good English communication skills, both written and verbal, are essential along with the ability to maintain accurate care records.\n\nCandidates must be vigilant, responsive, and able to respond appropriately to emergencies as they arise. Candidates must be able to meet the physical demands of the role, as it will involve supporting individuals with moving and positioning in a safe, dignified manner.\n\nYour role will include:\n- Providing respectful, dignified personal care and emotional support to people according to their needs and preferences\n- Preparing meals and refreshments and supporting people with nutrition & hydration\n- Assisting with household and everyday living tasks, involving people as fully as possible to maintain their independence\n- Supporting people to take medication and administering medication as needed\n- Enabling people to take part in activities within the scheme and to enjoy relationships with others\n- Supporting residents to maximize their health & wellbeing, independence and quality of life\n- Responding to changing needs and emergencies and supporting people to live safely\n- Working positively with each person supported and their family, health professionals and housing officers to provide a coordinated service which meets their desired outcomes\n\nExperience of providing care and support is desirable but not essential as full training is provided.\n\nVacancy Reference Number:93571\n\nApplications for this role must be submitted via the Creative Support website using the above vacancy reference number\n\nFull training is provided, as is the opportunity to work towards QCF Diploma in Health and Social Care. Benefits of working with Creative Support include a probationary bonus, pension contributions, 28 days Leave and company paid enhanced DBS.\n\nWe are a passionate, inclusive, and anti-racist organization - Stonewall Diversity Champion, Disability Confident Employer who have recently received Investors in People Gold award.\n\nApplications are reviewed as they are received, we do not provide feedback for unsuccessful applications. We can only accept applications from candidates who are located in and eligible to work within the UK",
    "apply_url": "https://www.jobg8.com/Traffic.aspx?eq2PR%2bX5ctwVYyoplHnQEg4AdMbUlw9Jp",
    "source": "JobG8"
  },
  {
    "job_id": "b4bb895f-a331-4a46-8e07-0ee304e17c4f",
    "title": "Relief Extra Care Support Worker",
    "company": "Creative Support Ltd - Company - Temporary",
    "location": "Barnsley",
    "region": "South Yorkshire",
    "country": "UK",
    "category": "Support Worker – Wide",
    "employment_type": "Temporary",
    "salary_min": "13.21",
    "salary_max": "13.21",
    "salary_text": "£13.21 per hour",
    "posted_date": "",
    "description": "We are seeking warm, caring individuals to provide personalised care and support on a relief basis at our extra care services, Fitzwilliam Court, in Hoyland, Barnsley. Fitzwilliam Court supports older people maintain their wellbeing and enjoy active, independent lifestyles. We offer a variety of shifts to meet your needs.\n\nYou will provide respectful and dignified personal care, emotional support, meal preparation, and assistance with daily tasks to maintain independence. Supporting medication management, encouraging participation in activities, and fostering social connections are key aspects of the role. You will also respond to changing needs and emergencies to ensure safe living environments.\n\nA minimum of twelve months experience in care and support is essential. You must be compassionate, respectful, reliable, and accountable, with a strong duty of care. A reasonable standard of verbal and written English is necessary. You must be vigilant, responsive, and capable of handling the physical demands of the role.\n\nThis is a perfect Career opportunity for people who are keen to learn new skills, and are seeking a rewarding job that will allow them to progress in the health and social care sector.\n\nThe service has great Public transport links and is based along a bus route.\n\nVacancy Reference Number: 90438\n\nApplications for this role must be submitted via the Creative Support website using the above vacancy reference number\n\nWe are a passionate, inclusive, and anti-racist organization - Stonewall Diversity Champion, Disability Confident Employer who have recently received Investors in People Gold awarded.\n\nApplications are reviewed as they are received, we do not provide feedback for unsuccessful applications. We can only accept applications from candidates who are located in and eligible to work within the UK - This post will not be open to Sponsorship under the UKVI scheme, and we are unable to accept applicants with Skilled Worker Visas.",
    "apply_url": "https://www.jobg8.com/Traffic.aspx?aIHQjUdXakMCOL9R9JFEWLqRQTjEX7Nrr",
    "source": "JobG8"
  }
]